Metadata-Version: 2.4
Name: xlstm
Version: 2.0.5
Summary: A novel LSTM variant with promising performance compared to Transformers or State Space Models.
Author-email: Maximilian Beck <beck@ml.jku.at>, Korbinian Poeppel <poeppel@ml.jku.at>, Andreas Auer <auer@ml.jku.at>
License: 
Project-URL: Repository, https://github.com/NX-AI/xlstm
Project-URL: Issues, https://github.com/NX-AI/xlstm/issues
Keywords: LSTM,Transformer,Machine Learning,Deep Learning,State Space Models
Classifier: Programming Language :: Python :: 3
Classifier: Operating System :: OS Independent
Requires-Python: >=3.9
License-File: LICENSE
License-File: AUTHORS
Requires-Dist: torch
Requires-Dist: einops
Requires-Dist: numpy
Requires-Dist: opt_einsum
Requires-Dist: omegaconf
Requires-Dist: transformers
Requires-Dist: reportlab
Requires-Dist: joypy
Requires-Dist: ipykernel
Requires-Dist: dacite
Requires-Dist: ftfy
Requires-Dist: ninja
Requires-Dist: huggingface-hub
Requires-Dist: rich
Requires-Dist: tokenizers
Requires-Dist: tqdm
Requires-Dist: seaborn
Requires-Dist: mlstm_kernels
Dynamic: license-file
